{"vVYfyWHZoSJ7O8wgPi8FPA==":"mbr-96x80.png","tWnc/46apN5aZ9dohvW6pg==":"mbr-1920x1173.jpg","2KtkWz2nm3uZkVixRTejEA==":"mbr-815x833.png","+JKIrtrzSyXR28K00aeQwg==":"mbr-815x545.jpg","bZh1PUO/yx4gKTwwzcJqsQ==":"mbr-815x504.png","dbIRwmQlcK8L0tZvmKbExw==":"mbr-815x776.jpg","ayBJBf6Co6mm4wSvy87q+A==":"mbr-815x873.png","0oydMdAx2twWSl0GWnj+Ng==":"mbr-1-815x873.png","PASb8qwSh7aebhigsTP3Sg==":"mbr-815x771.png","IG96PvrTJPm/sh+9u4XAXQ==":"mbr-1920x1280.png","hHnKnkN6Tv1uhdEfuO51bA==":"mbr-1-815x771.png"}